groovegenerator/__init__.py
groovegenerator/groovegenerator.py
groovegenerator/samples/909hihatStereo.wav
groovegenerator/samples/909kickStereo.wav
groovegenerator/samples/909snareStereo.wav
groovegenerator/samples/amenKick.wav
groovegenerator/samples/amenKickLong.wav
groovegenerator/samples/amenRide.wav
groovegenerator/samples/amenRideLong.wav
groovegenerator/samples/amenSnare.wav
groovegenerator/samples/amenSnareLong.wav
groovegenerator/samples/hihat.wav
groovegenerator/samples/kick.wav
groovegenerator/samples/snare.wav
ignore/__init__.py
ignore/groovegenerator.py
ignore/samples/hihat.wav
ignore/samples/kick.wav
ignore/samples/snare.wav
groovegenerator-0.1.5.dist-info/LICENSE
groovegenerator-0.1.5.dist-info/METADATA
groovegenerator-0.1.5.dist-info/WHEEL
groovegenerator-0.1.5.dist-info/top_level.txt
groovegenerator-0.1.5.dist-info/RECORD
