Metadata-Version: 2.1
Name: groovegenerator
Version: 0.1.5
Summary: Collection of functions to generate and analyse rhythm patterns.
Home-page: https://github.com/OleAd/GrooveGenDist/
Author: Ole Adrian Heggli
Author-email: oleheggli@gmail.com
License: MIT License
Platform: UNKNOWN
License-File: LICENSE
Requires-Dist: numpy (>=1.21.2)
Requires-Dist: pandas (>=1.3.3)
Requires-Dist: mido (>=1.2.10)
Requires-Dist: scipy (>=1.7.1)
